paralang_base/__init__.py
paralang_base/const.py
paralang_base/exceptions.py
paralang_base/abc/__init__.py
paralang_base/abc/base_ctx.py
paralang_base/abc/base_error_handler.py
paralang_base/abc/base_stream.py
paralang_base/abc/base_tokens.py
paralang_base/compiler/__init__.py
paralang_base/compiler/compile_ctx.py
paralang_base/compiler/compiler.py
paralang_base/compiler/error_handler.py
paralang_base/compiler/linker.py
paralang_base/compiler/optimiser.py
paralang_base/compiler/parse_stream.py
paralang_base/compiler/parse_tokens.py
paralang_base/compiler/process.py
paralang_base/compiler/parser/__init__.py
paralang_base/compiler/parser/listener.py
paralang_base/compiler/parser/python/ParaLexer.py
paralang_base/compiler/parser/python/ParaListener.py
paralang_base/compiler/parser/python/ParaParser.py
paralang_base/compiler/parser/python/__init__.py
paralang_base/preprocessor/__init__.py
paralang_base/preprocessor/__main__.py
paralang_base/preprocessor/ctx.py
paralang_base/preprocessor/error_handler.py
paralang_base/preprocessor/listener.py
paralang_base/preprocessor/parse_stream.py
paralang_base/preprocessor/parse_tokens.py
paralang_base/preprocessor/abc/__init__.py
paralang_base/preprocessor/abc/base_token.py
paralang_base/preprocessor/parser/ParaPreProcessorLexer.py
paralang_base/preprocessor/parser/ParaPreProcessorListener.py
paralang_base/preprocessor/parser/ParaPreProcessorParser.py
paralang_base/preprocessor/parser/__init__.py
paralang_base/proj_conf/__init__.py
paralang_base/util/__init__.py
paralang_base/util/c_compiler.py
paralang_base/util/cleanup_man.py
paralang_base/util/decorators.py
paralang_base/util/parser_ctx_tools.py
paralang_base/util/pathtools.py
paralang_base/util/stream.py
paralang_base/util/strtools.py
paralang_base-0.1.dev7.dist-info/LICENSE
paralang_base-0.1.dev7.dist-info/METADATA
paralang_base-0.1.dev7.dist-info/WHEEL
paralang_base-0.1.dev7.dist-info/top_level.txt
paralang_base-0.1.dev7.dist-info/RECORD
