Metadata-Version: 2.1
Name: paralang-base
Version: 0.1.dev7
Summary: Python-Compiler and API for the Para language
Home-page: https://github.com/Para-Lang/Para/
Author: Luna Klatzer
Author-email: luna.klatzer@gmail.com
Maintainer: Luna Klatzer
Maintainer-email: luna.klatzer@gmail.com
License: GNU GENERAL PUBLIC LICENSE v3.0
Project-URL: Issue-Page, https://github.com/Para-Lang/Para/issues/
Project-URL: Changelog, https://github.com/Para-Lang/Para/releases
Project-URL: Docs, https://para.readthedocs.org/
Platform: UNKNOWN
Classifier: Development Status :: 2 - Pre-Alpha
Classifier: Programming Language :: Python :: 3
Classifier: Programming Language :: Python :: 3.8
Classifier: Programming Language :: Python :: 3.9
Classifier: Programming Language :: Python :: 3.10
Classifier: Programming Language :: C
Classifier: License :: OSI Approved :: GNU General Public License v3 (GPLv3)
Classifier: Environment :: Console
Classifier: Environment :: Other Environment
Classifier: Topic :: Software Development :: Code Generators
Classifier: Topic :: Software Development :: Compilers
Classifier: Intended Audience :: Developers
Classifier: Intended Audience :: Information Technology
Classifier: Operating System :: POSIX
Classifier: Operating System :: MacOS :: MacOS X
Classifier: Operating System :: Microsoft :: Windows
Requires-Python: >=3.8
License-File: LICENSE
Requires-Dist: antlr4-python3-runtime (>=4.9)
Requires-Dist: cached-property (>=1.5.1)
